symmetrize/__init__.py
symmetrize/pointops.py
symmetrize/sym.py
symmetrize/tps.py
symmetrize-0.5.5.dist-info/METADATA
symmetrize-0.5.5.dist-info/WHEEL
symmetrize-0.5.5.dist-info/top_level.txt
symmetrize-0.5.5.dist-info/RECORD
