Metadata-Version: 2.1
Name: symmetrize
Version: 0.5.5
Summary: Symmetrization and centering of 2D pattern using nonrigid point set registration
Home-page: https://github.com/RealPolitiX/symmetrize
Author: R. Patrick Xian
Author-email: xrpatrick@gmail.com
License: UNKNOWN
Platform: UNKNOWN
Classifier: Development Status :: 2 - Pre-Alpha
Classifier: Operating System :: MacOS :: MacOS X
Classifier: Operating System :: Microsoft :: Windows
Classifier: Programming Language :: Python
Classifier: Programming Language :: Python :: 2
Classifier: Programming Language :: Python :: 2.7
Classifier: Programming Language :: Python :: 3
Classifier: Programming Language :: Python :: 3.4
Classifier: Programming Language :: Python :: 3.5
Classifier: Programming Language :: Python :: 3.6
Requires-Dist: numpy
Requires-Dist: scipy
Requires-Dist: scikit-image
Requires-Dist: matplotlib
Requires-Dist: astropy
Requires-Dist: photutils
Requires-Dist: opencv-python
Requires-Dist: sphinx-rtd-theme
Requires-Dist: sphinx
Requires-Dist: recommonmark
